Metadata-Version: 2.1
Name: trylmz1
Version: 0.0.15
Summary: This is a deep learning based library for handling Turkish clitics such as da, de, ki and mi.
Home-page: UNKNOWN
Author: Ümit Yılmaz
Author-email: umitylmz98@gmail.com
License: UNKNOWN
Platform: UNKNOWN
Classifier: Programming Language :: Python :: 3
Classifier: License :: OSI Approved :: MIT License
Classifier: Operating System :: OS Independent
Requires-Python: >=3.6
